vuejspython/__init__.py
vuejspython/fsapi.js
vuejspython/index.html
vuejspython/run.py
vuejspython/serve.py
vuejspython/vue.esm-browser.prod.js
vuejspython/vue3-sfc-loader.esm.js
vuejspython/builtin/create-demo-files.vue
vuejspython/builtin/diff.min.js
vuejspython/builtin/edit-file.vue
vuejspython/builtin/exam-toggle.vue
vuejspython/builtin/file-rotator.vue
vuejspython/builtin/rotate-files.vue
vuejspython/builtin/serve-videos.vue
vuejspython/builtin/toggle-exam.vue
vuejspython/builtin/video-serve.vue
vuejspython/builtin/video-serve.vue~
vuejspython/builtin/view-file.vue
vuejspython/observablecollections/__init__.py
vuejspython/observablecollections/event.py
vuejspython/observablecollections/observable.py
vuejspython/observablecollections/observabledict.py
vuejspython/observablecollections/observablelist.py
vuejspython/observablecollections/observableset.py
vuejspython/static/__init__.py
vuejspython/static/picnic.min.css
vuejspython/static/vue.js
vuejspython/static/vue.min.js
vuejspython/static/vuejspython.js
vuejspython-1.0.6.dist-info/LICENSE
vuejspython-1.0.6.dist-info/METADATA
vuejspython-1.0.6.dist-info/WHEEL
vuejspython-1.0.6.dist-info/entry_points.txt
vuejspython-1.0.6.dist-info/top_level.txt
vuejspython-1.0.6.dist-info/RECORD
