Metadata-Version: 2.1
Name: vuejspython
Version: 1.0.6
Summary: Vuejs runner, with filesystem, and allowing python extension (e.g., to leverage numpy)
Home-page: https://github.com/twitwi/vuejs-python/
Author: Rémi Emonet
Author-email: remi+242-e2f8@heeere.com
Classifier: Programming Language :: Python :: 3
Classifier: License :: OSI Approved :: MIT License
Classifier: Operating System :: OS Independent
License-File: LICENSE
Requires-Dist: fastapi
Requires-Dist: uvicorn
